{"meta":{"builtAt":"2026-07-07T18:31:27+00:00","source":"official","stagesComplete":[1,2,3,4],"asOfStage":4,"note":"Fantasy points are the official Tissot game scores. Per-rider totals are cumulative; per-stage figures appear as daily snapshots accumulate."},"teams":["Alpecin-Premier Tech","Bahrain Victorious","Caja Rural-Seguros RGA","Cofidis","Decathlon CMA CGM Team","EF Education - Easypost","Groupama-FDJ United","Lidl-Trek","Lotto Intermarché","Movistar Team","NSN Cycling Team","Netcompany Ineos","Pinarello-Q.36.5 Pro Cycling Team","Red Bull - BORA - hansgrohe","Soudal Quick-Step","Team Jayco AlUla","Team Picnic PostNL","Team Visma | Lease a Bike","TotalEnergies","Tudor Pro Cycling Team","UAE Team Emirates XRG","Uno-X Mobility","XDS Astana Team"],"riders":[{"id":"t-pogacar","name":"T. POGACAR","bib":"1","cost":27,"cat":"Leaders","team":20,"total":692,"avg":173.0,"nbMatchs":4,"breakdown":{"finishes":371,"climbsSprints":3,"combativity":0,"gc":170,"points":78,"kom":70,"youth":0},"stagePts":{"3":297,"4":77}},{"id":"j-vingegaard hansen","name":"J. VINGEGAARD HANSEN","bib":"11","cost":24,"cat":"Leaders","team":17,"total":548,"avg":137.0,"nbMatchs":4,"breakdown":{"finishes":279,"climbsSprints":1,"combativity":0,"gc":175,"points":64,"kom":29,"youth":0},"stagePts":{"3":225,"4":56}},{"id":"i-del toro romero","name":"I. DEL TORO ROMERO","bib":"2","cost":22,"cat":"Climbers","team":20,"total":547,"avg":136.8,"nbMatchs":4,"breakdown":{"finishes":281,"climbsSprints":0,"combativity":0,"gc":122,"points":70,"kom":0,"youth":74},"stagePts":{"3":137,"4":64}},{"id":"m-pedersen","name":"M. PEDERSEN","bib":"33","cost":18,"cat":"Sprinters","team":7,"total":508,"avg":127.0,"nbMatchs":4,"breakdown":{"finishes":213,"climbsSprints":239,"combativity":0,"gc":2,"points":54,"kom":0,"youth":0},"stagePts":{"3":102,"4":373}},{"id":"r-garcia pierna","name":"R. GARCIA PIERNA","bib":"144","cost":10,"cat":"All-rounders","team":9,"total":427,"avg":106.8,"nbMatchs":4,"breakdown":{"finishes":127,"climbsSprints":216,"combativity":0,"gc":29,"points":1,"kom":42,"youth":12},"stagePts":{"3":135,"4":272}},{"id":"a-molenaar","name":"A. MOLENAAR","bib":"224","cost":5,"cat":"All-rounders","team":2,"total":420,"avg":105.0,"nbMatchs":4,"breakdown":{"finishes":34,"climbsSprints":255,"combativity":0,"gc":11,"points":44,"kom":76,"youth":0},"stagePts":{"3":37,"4":152}},{"id":"r-evenepoel","name":"R. EVENEPOEL","bib":"21","cost":20,"cat":"Leaders","team":13,"total":410,"avg":102.5,"nbMatchs":4,"breakdown":{"finishes":200,"climbsSprints":0,"combativity":0,"gc":136,"points":52,"kom":22,"youth":0},"stagePts":{"3":123,"4":43}},{"id":"m-vacek","name":"M. VACEK","bib":"37","cost":10,"cat":"All-rounders","team":7,"total":369,"avg":92.2,"nbMatchs":4,"breakdown":{"finishes":78,"climbsSprints":180,"combativity":0,"gc":65,"points":0,"kom":8,"youth":38},"stagePts":{"3":19,"4":303}},{"id":"a-baudin","name":"A. BAUDIN","bib":"43","cost":10,"cat":"Climbers","team":5,"total":358,"avg":89.5,"nbMatchs":4,"breakdown":{"finishes":43,"climbsSprints":143,"combativity":30,"gc":51,"points":2,"kom":60,"youth":29},"stagePts":{"3":227,"4":45}},{"id":"p-seixas","name":"P. SEIXAS","bib":"51","cost":19,"cat":"Leaders","team":4,"total":353,"avg":88.2,"nbMatchs":4,"breakdown":{"finishes":174,"climbsSprints":0,"combativity":0,"gc":98,"points":23,"kom":0,"youth":58},"stagePts":{"3":158,"4":45}},{"id":"q-simmons","name":"Q. SIMMONS","bib":"34","cost":15,"cat":"All-rounders","team":7,"total":330,"avg":82.5,"nbMatchs":4,"breakdown":{"finishes":167,"climbsSprints":130,"combativity":0,"gc":11,"points":20,"kom":0,"youth":2},"stagePts":{"3":10,"4":307}},{"id":"t-johannessen","name":"T. JOHANNESSEN","bib":"121","cost":17,"cat":"Leaders","team":21,"total":320,"avg":80.0,"nbMatchs":4,"breakdown":{"finishes":177,"climbsSprints":2,"combativity":0,"gc":70,"points":38,"kom":33,"youth":0},"stagePts":{"3":140,"4":35}},{"id":"j-ayuso pesquera","name":"J. AYUSO PESQUERA","bib":"31","cost":20,"cat":"Leaders","team":7,"total":305,"avg":76.2,"nbMatchs":4,"breakdown":{"finishes":118,"climbsSprints":0,"combativity":0,"gc":117,"points":0,"kom":0,"youth":70},"stagePts":{"3":103,"4":41}},{"id":"r-debruyne","name":"R. DEBRUYNE","bib":"102","cost":10,"cat":"All-rounders","team":0,"total":296,"avg":74.0,"nbMatchs":4,"breakdown":{"finishes":109,"climbsSprints":121,"combativity":0,"gc":42,"points":0,"kom":1,"youth":23},"stagePts":{"3":22,"4":256}},{"id":"k-vauquelin","name":"K. VAUQUELIN","bib":"88","cost":15,"cat":"Leaders","team":11,"total":289,"avg":72.2,"nbMatchs":4,"breakdown":{"finishes":105,"climbsSprints":123,"combativity":0,"gc":26,"points":26,"kom":0,"youth":9},"stagePts":{"3":7,"4":211}},{"id":"p-castrillo zapater","name":"P. CASTRILLO ZAPATER","bib":"142","cost":11,"cat":"Climbers","team":9,"total":282,"avg":70.5,"nbMatchs":4,"breakdown":{"finishes":69,"climbsSprints":143,"combativity":30,"gc":23,"points":0,"kom":6,"youth":11},"stagePts":{"3":17,"4":255}},{"id":"t-traeen","name":"T. TRÆEN","bib":"127","cost":10,"cat":"Climbers","team":21,"total":279,"avg":69.8,"nbMatchs":4,"breakdown":{"finishes":83,"climbsSprints":119,"combativity":0,"gc":77,"points":0,"kom":0,"youth":0},"stagePts":{"3":20,"4":231}},{"id":"r-gregoire","name":"R. GREGOIRE","bib":"181","cost":14,"cat":"All-rounders","team":6,"total":274,"avg":68.5,"nbMatchs":4,"breakdown":{"finishes":89,"climbsSprints":79,"combativity":0,"gc":55,"points":6,"kom":18,"youth":27},"stagePts":{"3":7,"4":93}},{"id":"f-van den broek","name":"F. VAN DEN BROEK","bib":"218","cost":11,"cat":"All-rounders","team":16,"total":269,"avg":67.2,"nbMatchs":4,"breakdown":{"finishes":26,"climbsSprints":202,"combativity":0,"gc":6,"points":13,"kom":22,"youth":0},"stagePts":{"3":7,"4":116}},{"id":"s-quinn","name":"S. QUINN","bib":"45","cost":9,"cat":"All-rounders","team":5,"total":269,"avg":67.2,"nbMatchs":4,"breakdown":{"finishes":89,"climbsSprints":112,"combativity":0,"gc":68,"points":0,"kom":0,"youth":0},"stagePts":{"3":15,"4":227}},{"id":"v-van mechelen","name":"V. VAN MECHELEN","bib":"78","cost":8,"cat":"All-rounders","team":1,"total":260,"avg":65.0,"nbMatchs":4,"breakdown":{"finishes":50,"climbsSprints":175,"combativity":0,"gc":7,"points":0,"kom":28,"youth":0},"stagePts":{"3":117,"4":134}},{"id":"f-engelhardt","name":"F. ENGELHARDT","bib":"114","cost":9,"cat":"All-rounders","team":15,"total":256,"avg":64.0,"nbMatchs":4,"breakdown":{"finishes":8,"climbsSprints":159,"combativity":30,"gc":0,"points":21,"kom":38,"youth":0},"stagePts":{"3":19,"4":4}},{"id":"r-carapaz","name":"R. CARAPAZ","bib":"41","cost":19,"cat":"Leaders","team":5,"total":250,"avg":62.5,"nbMatchs":4,"breakdown":{"finishes":164,"climbsSprints":2,"combativity":0,"gc":54,"points":14,"kom":16,"youth":0},"stagePts":{"3":153,"4":21}},{"id":"m-frigo","name":"M. FRIGO","bib":"134","cost":8,"cat":"Climbers","team":10,"total":247,"avg":61.8,"nbMatchs":4,"breakdown":{"finishes":104,"climbsSprints":120,"combativity":0,"gc":5,"points":0,"kom":18,"youth":0},"stagePts":{"3":0,"4":241}},{"id":"l-martinez","name":"L. MARTINEZ","bib":"71","cost":15,"cat":"Climbers","team":1,"total":243,"avg":60.8,"nbMatchs":4,"breakdown":{"finishes":115,"climbsSprints":0,"combativity":0,"gc":81,"points":3,"kom":0,"youth":44},"stagePts":{"3":78,"4":31}},{"id":"m-skjelmose","name":"M. SKJELMOSE","bib":"35","cost":17,"cat":"Climbers","team":7,"total":236,"avg":59.0,"nbMatchs":4,"breakdown":{"finishes":158,"climbsSprints":0,"combativity":0,"gc":53,"points":25,"kom":0,"youth":0},"stagePts":{"3":75,"4":21}},{"id":"l-van eetvelt","name":"L. VAN EETVELT","bib":"156","cost":12,"cat":"Climbers","team":8,"total":223,"avg":55.8,"nbMatchs":4,"breakdown":{"finishes":131,"climbsSprints":0,"combativity":0,"gc":53,"points":8,"kom":0,"youth":31},"stagePts":{"3":116,"4":25}},{"id":"f-lipowitz","name":"F. LIPOWITZ","bib":"25","cost":20,"cat":"Leaders","team":13,"total":204,"avg":51.0,"nbMatchs":4,"breakdown":{"finishes":110,"climbsSprints":0,"combativity":0,"gc":94,"points":0,"kom":0,"youth":0},"stagePts":{"3":96,"4":23}},{"id":"n-prodhomme","name":"N. PRODHOMME","bib":"57","cost":12,"cat":"Climbers","team":4,"total":189,"avg":47.2,"nbMatchs":4,"breakdown":{"finishes":20,"climbsSprints":106,"combativity":0,"gc":15,"points":0,"kom":48,"youth":0},"stagePts":{"3":144,"4":30}},{"id":"m-matthews","name":"M. MATTHEWS","bib":"115","cost":15,"cat":"Sprinters","team":15,"total":180,"avg":45.0,"nbMatchs":4,"breakdown":{"finishes":60,"climbsSprints":96,"combativity":0,"gc":24,"points":0,"kom":0,"youth":0},"stagePts":{"3":4,"4":143}},{"id":"n-oliveira","name":"N. OLIVEIRA","bib":"146","cost":8,"cat":"All-rounders","team":9,"total":173,"avg":43.2,"nbMatchs":4,"breakdown":{"finishes":8,"climbsSprints":154,"combativity":0,"gc":11,"points":0,"kom":0,"youth":0},"stagePts":{"3":74,"4":90}},{"id":"j-tratnik","name":"J. TRATNIK","bib":"26","cost":8,"cat":"All-rounders","team":13,"total":164,"avg":41.0,"nbMatchs":4,"breakdown":{"finishes":19,"climbsSprints":129,"combativity":0,"gc":0,"points":0,"kom":16,"youth":0},"stagePts":{"3":0,"4":152}},{"id":"i-van wilder","name":"I. VAN WILDER","bib":"97","cost":13,"cat":"Climbers","team":14,"total":161,"avg":40.2,"nbMatchs":4,"breakdown":{"finishes":91,"climbsSprints":0,"combativity":0,"gc":70,"points":0,"kom":0,"youth":0},"stagePts":{"3":66,"4":18}},{"id":"t-pidcock","name":"T. PIDCOCK","bib":"171","cost":18,"cat":"Leaders","team":12,"total":158,"avg":39.5,"nbMatchs":4,"breakdown":{"finishes":88,"climbsSprints":0,"combativity":0,"gc":70,"points":0,"kom":0,"youth":0},"stagePts":{"3":45,"4":18}},{"id":"d-piganzoli","name":"D. PIGANZOLI","bib":"18","cost":16,"cat":"Climbers","team":17,"total":156,"avg":39.0,"nbMatchs":4,"breakdown":{"finishes":45,"climbsSprints":0,"combativity":0,"gc":68,"points":0,"kom":0,"youth":43},"stagePts":{"3":35,"4":24}},{"id":"b-girmay","name":"B. GIRMAY","bib":"131","cost":19,"cat":"Sprinters","team":10,"total":147,"avg":36.8,"nbMatchs":4,"breakdown":{"finishes":2,"climbsSprints":120,"combativity":0,"gc":1,"points":24,"kom":0,"youth":0},"stagePts":{"3":0,"4":118}},{"id":"a-delettre","name":"A. DELETTRE","bib":"204","cost":9,"cat":"All-rounders","team":18,"total":147,"avg":36.8,"nbMatchs":4,"breakdown":{"finishes":52,"climbsSprints":90,"combativity":0,"gc":5,"points":0,"kom":0,"youth":0},"stagePts":{"3":2,"4":138}},{"id":"m-vercher","name":"M. VERCHER","bib":"208","cost":9,"cat":"All-rounders","team":18,"total":146,"avg":36.5,"nbMatchs":4,"breakdown":{"finishes":9,"climbsSprints":118,"combativity":0,"gc":13,"points":0,"kom":6,"youth":0},"stagePts":{"3":132,"4":4}},{"id":"j-stuyven","name":"J. STUYVEN","bib":"94","cost":12,"cat":"All-rounders","team":14,"total":140,"avg":35.0,"nbMatchs":4,"breakdown":{"finishes":41,"climbsSprints":92,"combativity":0,"gc":7,"points":0,"kom":0,"youth":0},"stagePts":{"3":2,"4":127}},{"id":"i-izagirre insausti","name":"I. IZAGIRRE INSAUSTI","bib":"161","cost":12,"cat":"Climbers","team":3,"total":135,"avg":33.8,"nbMatchs":4,"breakdown":{"finishes":21,"climbsSprints":80,"combativity":0,"gc":34,"points":0,"kom":0,"youth":0},"stagePts":{"3":10,"4":97}},{"id":"a-kirsch","name":"A. KIRSCH","bib":"166","cost":6,"cat":"All-rounders","team":3,"total":133,"avg":33.2,"nbMatchs":4,"breakdown":{"finishes":10,"climbsSprints":120,"combativity":0,"gc":3,"points":0,"kom":0,"youth":0},"stagePts":{"3":0,"4":128}},{"id":"j-philipsen","name":"J. PHILIPSEN","bib":"105","cost":22,"cat":"Sprinters","team":0,"total":132,"avg":33.0,"nbMatchs":4,"breakdown":{"finishes":9,"climbsSprints":111,"combativity":0,"gc":0,"points":12,"kom":0,"youth":0},"stagePts":{"3":0,"4":107}},{"id":"g-bennett","name":"G. BENNETT","bib":"133","cost":11,"cat":"Climbers","team":10,"total":131,"avg":32.8,"nbMatchs":4,"breakdown":{"finishes":10,"climbsSprints":91,"combativity":0,"gc":29,"points":0,"kom":1,"youth":0},"stagePts":{"3":104,"4":6}},{"id":"q-hermans","name":"Q. HERMANS","bib":"174","cost":11,"cat":"All-rounders","team":12,"total":125,"avg":31.2,"nbMatchs":4,"breakdown":{"finishes":27,"climbsSprints":80,"combativity":0,"gc":18,"points":0,"kom":0,"youth":0},"stagePts":{"3":6,"4":101}},{"id":"g-steinhauser","name":"G. STEINHAUSER","bib":"46","cost":13,"cat":"All-rounders","team":5,"total":122,"avg":30.5,"nbMatchs":4,"breakdown":{"finishes":10,"climbsSprints":93,"combativity":0,"gc":14,"points":0,"kom":0,"youth":5},"stagePts":{"3":1,"4":94}},{"id":"b-mcnulty","name":"B. MCNULTY","bib":"4","cost":16,"cat":"Climbers","team":20,"total":119,"avg":29.8,"nbMatchs":4,"breakdown":{"finishes":32,"climbsSprints":4,"combativity":0,"gc":25,"points":0,"kom":58,"youth":0},"stagePts":{"3":36,"4":27}},{"id":"g-zimmermann","name":"G. ZIMMERMANN","bib":"158","cost":11,"cat":"Climbers","team":8,"total":113,"avg":28.2,"nbMatchs":4,"breakdown":{"finishes":26,"climbsSprints":79,"combativity":0,"gc":8,"points":0,"kom":0,"youth":0},"stagePts":{"3":6,"4":101}},{"id":"e-bernal gomez","name":"E. BERNAL GOMEZ","bib":"81","cost":16,"cat":"Leaders","team":11,"total":112,"avg":28.0,"nbMatchs":4,"breakdown":{"finishes":48,"climbsSprints":5,"combativity":0,"gc":29,"points":30,"kom":0,"youth":0},"stagePts":{"3":35,"4":10}},{"id":"e-planckaert","name":"E. PLANCKAERT","bib":"106","cost":8,"cat":"All-rounders","team":0,"total":111,"avg":27.8,"nbMatchs":4,"breakdown":{"finishes":16,"climbsSprints":94,"combativity":0,"gc":1,"points":0,"kom":0,"youth":0},"stagePts":{"3":0,"4":102}},{"id":"h-tejada canacue","name":"H. TEJADA CANACUE","bib":"65","cost":13,"cat":"Climbers","team":22,"total":110,"avg":27.5,"nbMatchs":4,"breakdown":{"finishes":17,"climbsSprints":62,"combativity":0,"gc":31,"points":0,"kom":0,"youth":0},"stagePts":{"3":80,"4":9}},{"id":"p-eenkhoorn","name":"P. EENKHOORN","bib":"92","cost":8,"cat":"All-rounders","team":14,"total":110,"avg":27.5,"nbMatchs":4,"breakdown":{"finishes":18,"climbsSprints":87,"combativity":0,"gc":5,"points":0,"kom":0,"youth":0},"stagePts":{"3":3,"4":97}},{"id":"n-denz","name":"N. DENZ","bib":"23","cost":7,"cat":"All-rounders","team":13,"total":108,"avg":27.0,"nbMatchs":4,"breakdown":{"finishes":20,"climbsSprints":87,"combativity":0,"gc":1,"points":0,"kom":0,"youth":0},"stagePts":{"3":0,"4":96}},{"id":"e-costiou","name":"E. COSTIOU","bib":"184","cost":10,"cat":"Climbers","team":6,"total":105,"avg":26.2,"nbMatchs":4,"breakdown":{"finishes":18,"climbsSprints":83,"combativity":0,"gc":4,"points":0,"kom":0,"youth":0},"stagePts":{"3":1,"4":91}},{"id":"t-arensman","name":"T. ARENSMAN","bib":"82","cost":17,"cat":"Leaders","team":11,"total":103,"avg":25.8,"nbMatchs":4,"breakdown":{"finishes":38,"climbsSprints":0,"combativity":0,"gc":47,"points":18,"kom":0,"youth":0},"stagePts":{"3":25,"4":12}},{"id":"r-stannard","name":"R. STANNARD","bib":"76","cost":10,"cat":"All-rounders","team":1,"total":103,"avg":25.8,"nbMatchs":4,"breakdown":{"finishes":11,"climbsSprints":91,"combativity":0,"gc":1,"points":0,"kom":0,"youth":0},"stagePts":{"3":1,"4":91}},{"id":"j-nicolau beltran","name":"J. NICOLAU BELTRAN","bib":"225","cost":6,"cat":"Climbers","team":2,"total":102,"avg":25.5,"nbMatchs":4,"breakdown":{"finishes":16,"climbsSprints":84,"combativity":0,"gc":2,"points":0,"kom":0,"youth":0},"stagePts":{"3":3,"4":93}},{"id":"b-van moer","name":"B. VAN MOER","bib":"177","cost":9,"cat":"All-rounders","team":12,"total":101,"avg":25.2,"nbMatchs":4,"breakdown":{"finishes":14,"climbsSprints":87,"combativity":0,"gc":0,"points":0,"kom":0,"youth":0},"stagePts":{"3":0,"4":95}},{"id":"j-delbove","name":"J. DELBOVE","bib":"203","cost":8,"cat":"All-rounders","team":18,"total":99,"avg":24.8,"nbMatchs":4,"breakdown":{"finishes":11,"climbsSprints":71,"combativity":0,"gc":13,"points":4,"kom":0,"youth":0},"stagePts":{"3":79,"4":3}},{"id":"c-uijtdebroeks","name":"C. UIJTDEBROEKS","bib":"141","cost":16,"cat":"Leaders","team":9,"total":92,"avg":23.0,"nbMatchs":4,"breakdown":{"finishes":30,"climbsSprints":0,"combativity":0,"gc":39,"points":0,"kom":0,"youth":23},"stagePts":{"3":28,"4":18}},{"id":"m-valgren","name":"M. VALGREN","bib":"47","cost":12,"cat":"All-rounders","team":5,"total":92,"avg":23.0,"nbMatchs":4,"breakdown":{"finishes":14,"climbsSprints":77,"combativity":0,"gc":1,"points":0,"kom":0,"youth":0},"stagePts":{"3":0,"4":85}},{"id":"a-balderstone roumens","name":"A. BALDERSTONE ROUMENS","bib":"222","cost":10,"cat":"Leaders","team":2,"total":92,"avg":23.0,"nbMatchs":4,"breakdown":{"finishes":13,"climbsSprints":53,"combativity":0,"gc":26,"points":0,"kom":0,"youth":0},"stagePts":{"3":61,"4":5}},{"id":"j-jegat","name":"J. JEGAT","bib":"201","cost":14,"cat":"Leaders","team":18,"total":91,"avg":22.8,"nbMatchs":4,"breakdown":{"finishes":47,"climbsSprints":0,"combativity":0,"gc":44,"points":0,"kom":0,"youth":0},"stagePts":{"3":49,"4":11}},{"id":"a-tiberi","name":"A. TIBERI","bib":"77","cost":15,"cat":"Leaders","team":1,"total":88,"avg":22.0,"nbMatchs":4,"breakdown":{"finishes":22,"climbsSprints":0,"combativity":0,"gc":42,"points":0,"kom":0,"youth":24},"stagePts":{"3":24,"4":13}},{"id":"l-plapp","name":"L. PLAPP","bib":"117","cost":13,"cat":"All-rounders","team":15,"total":88,"avg":22.0,"nbMatchs":4,"breakdown":{"finishes":11,"climbsSprints":62,"combativity":0,"gc":15,"points":0,"kom":0,"youth":0},"stagePts":{"3":64,"4":1}},{"id":"f-ganna","name":"F. GANNA","bib":"84","cost":18,"cat":"All-rounders","team":11,"total":85,"avg":21.2,"nbMatchs":4,"breakdown":{"finishes":19,"climbsSprints":0,"combativity":0,"gc":46,"points":0,"kom":20,"youth":0},"stagePts":{"3":0,"4":0}},{"id":"c-braz afonso","name":"C. BRAZ AFONSO","bib":"183","cost":8,"cat":"Climbers","team":6,"total":85,"avg":21.2,"nbMatchs":4,"breakdown":{"finishes":14,"climbsSprints":54,"combativity":0,"gc":17,"points":0,"kom":0,"youth":0},"stagePts":{"3":60,"4":4}},{"id":"m-cort nielsen","name":"M. CORT NIELSEN","bib":"124","cost":14,"cat":"All-rounders","team":21,"total":81,"avg":20.2,"nbMatchs":4,"breakdown":{"finishes":9,"climbsSprints":70,"combativity":0,"gc":2,"points":0,"kom":0,"youth":0},"stagePts":{"3":73,"4":3}},{"id":"l-vervaeke","name":"L. VERVAEKE","bib":"98","cost":7,"cat":"Climbers","team":14,"total":78,"avg":19.5,"nbMatchs":4,"breakdown":{"finishes":8,"climbsSprints":65,"combativity":0,"gc":5,"points":0,"kom":0,"youth":0},"stagePts":{"3":66,"4":2}},{"id":"s-higuita garcia","name":"S. HIGUITA GARCIA","bib":"61","cost":13,"cat":"Climbers","team":22,"total":77,"avg":19.2,"nbMatchs":4,"breakdown":{"finishes":41,"climbsSprints":0,"combativity":0,"gc":36,"points":0,"kom":0,"youth":0},"stagePts":{"3":43,"4":10}},{"id":"m-schmid","name":"M. SCHMID","bib":"118","cost":14,"cat":"Climbers","team":15,"total":75,"avg":18.8,"nbMatchs":4,"breakdown":{"finishes":12,"climbsSprints":56,"combativity":0,"gc":7,"points":0,"kom":0,"youth":0},"stagePts":{"3":59,"4":1}},{"id":"m-jorgenson","name":"M. JORGENSON","bib":"16","cost":18,"cat":"Climbers","team":17,"total":73,"avg":18.2,"nbMatchs":4,"breakdown":{"finishes":38,"climbsSprints":1,"combativity":0,"gc":22,"points":0,"kom":12,"youth":0},"stagePts":{"3":13,"4":10}},{"id":"m-storer","name":"M. STORER","bib":"196","cost":16,"cat":"Leaders","team":19,"total":73,"avg":18.2,"nbMatchs":4,"breakdown":{"finishes":6,"climbsSprints":64,"combativity":0,"gc":3,"points":0,"kom":0,"youth":0},"stagePts":{"3":69,"4":1}},{"id":"a-yates","name":"A. YATES","bib":"8","cost":19,"cat":"Leaders","team":20,"total":70,"avg":17.5,"nbMatchs":4,"breakdown":{"finishes":45,"climbsSprints":0,"combativity":0,"gc":25,"points":0,"kom":0,"youth":0},"stagePts":{"3":17,"4":15}},{"id":"a-aranburu deva","name":"A. ARANBURU DEVA","bib":"163","cost":13,"cat":"Sprinters","team":3,"total":69,"avg":17.2,"nbMatchs":4,"breakdown":{"finishes":10,"climbsSprints":46,"combativity":0,"gc":13,"points":0,"kom":0,"youth":0},"stagePts":{"3":49,"4":2}},{"id":"t-foss","name":"T. FOSS","bib":"83","cost":13,"cat":"All-rounders","team":11,"total":69,"avg":17.2,"nbMatchs":4,"breakdown":{"finishes":29,"climbsSprints":0,"combativity":0,"gc":40,"points":0,"kom":0,"youth":0},"stagePts":{"3":1,"4":1}},{"id":"s-kuss","name":"S. KUSS","bib":"17","cost":16,"cat":"Climbers","team":17,"total":66,"avg":16.5,"nbMatchs":4,"breakdown":{"finishes":40,"climbsSprints":0,"combativity":0,"gc":26,"points":0,"kom":0,"youth":0},"stagePts":{"3":16,"4":11}},{"id":"m-van der poel","name":"M. VAN DER POEL","bib":"101","cost":22,"cat":"All-rounders","team":0,"total":60,"avg":15.0,"nbMatchs":4,"breakdown":{"finishes":17,"climbsSprints":0,"combativity":0,"gc":43,"points":0,"kom":0,"youth":0},"stagePts":{"3":4,"4":3}},{"id":"t-benoot","name":"T. BENOOT","bib":"52","cost":11,"cat":"All-rounders","team":4,"total":58,"avg":14.5,"nbMatchs":4,"breakdown":{"finishes":33,"climbsSprints":0,"combativity":0,"gc":25,"points":0,"kom":0,"youth":0},"stagePts":{"3":24,"4":11}},{"id":"y-voisard","name":"Y. VOISARD","bib":"198","cost":9,"cat":"Climbers","team":19,"total":58,"avg":14.5,"nbMatchs":4,"breakdown":{"finishes":18,"climbsSprints":0,"combativity":0,"gc":40,"points":0,"kom":0,"youth":0},"stagePts":{"3":18,"4":10}},{"id":"j-hindley","name":"J. HINDLEY","bib":"24","cost":16,"cat":"Climbers","team":13,"total":55,"avg":13.8,"nbMatchs":4,"breakdown":{"finishes":26,"climbsSprints":0,"combativity":0,"gc":29,"points":0,"kom":0,"youth":0},"stagePts":{"3":15,"4":11}},{"id":"m-riccitello","name":"M. RICCITELLO","bib":"58","cost":16,"cat":"Climbers","team":4,"total":55,"avg":13.8,"nbMatchs":4,"breakdown":{"finishes":17,"climbsSprints":0,"combativity":0,"gc":24,"points":0,"kom":0,"youth":14},"stagePts":{"3":0,"4":3}},{"id":"j-parra cuerda","name":"J. PARRA CUERDA","bib":"228","cost":12,"cat":"Leaders","team":2,"total":53,"avg":13.2,"nbMatchs":4,"breakdown":{"finishes":17,"climbsSprints":0,"combativity":0,"gc":36,"points":0,"kom":0,"youth":0},"stagePts":{"3":16,"4":9}},{"id":"m-kwiatkowski","name":"M. KWIATKOWSKI","bib":"86","cost":12,"cat":"All-rounders","team":11,"total":47,"avg":11.8,"nbMatchs":4,"breakdown":{"finishes":21,"climbsSprints":0,"combativity":0,"gc":4,"points":22,"kom":0,"youth":0},"stagePts":{"3":0,"4":1}},{"id":"d-gee","name":"D. GEE","bib":"32","cost":16,"cat":"Leaders","team":7,"total":44,"avg":11.0,"nbMatchs":4,"breakdown":{"finishes":24,"climbsSprints":0,"combativity":0,"gc":20,"points":0,"kom":0,"youth":0},"stagePts":{"3":6,"4":9}},{"id":"d-godon","name":"D. GODON","bib":"85","cost":14,"cat":"Sprinters","team":11,"total":44,"avg":11.0,"nbMatchs":4,"breakdown":{"finishes":19,"climbsSprints":0,"combativity":0,"gc":5,"points":20,"kom":0,"youth":0},"stagePts":{"3":0,"4":0}},{"id":"v-paret peintre","name":"V. PARET PEINTRE","bib":"93","cost":14,"cat":"Climbers","team":14,"total":43,"avg":10.8,"nbMatchs":4,"breakdown":{"finishes":11,"climbsSprints":7,"combativity":0,"gc":13,"points":0,"kom":10,"youth":2},"stagePts":{"3":26,"4":7}},{"id":"m-van gils","name":"M. VAN GILS","bib":"28","cost":12,"cat":"All-rounders","team":13,"total":43,"avg":10.8,"nbMatchs":4,"breakdown":{"finishes":22,"climbsSprints":0,"combativity":0,"gc":21,"points":0,"kom":0,"youth":0},"stagePts":{"3":12,"4":9}},{"id":"g-martin guyonnet","name":"G. MARTIN GUYONNET","bib":"186","cost":13,"cat":"Leaders","team":6,"total":41,"avg":10.2,"nbMatchs":4,"breakdown":{"finishes":21,"climbsSprints":0,"combativity":0,"gc":20,"points":0,"kom":0,"youth":0},"stagePts":{"3":15,"4":8}},{"id":"a-paret peintre","name":"A. PARET PEINTRE","bib":"56","cost":11,"cat":"All-rounders","team":4,"total":39,"avg":9.8,"nbMatchs":4,"breakdown":{"finishes":20,"climbsSprints":0,"combativity":0,"gc":19,"points":0,"kom":0,"youth":0},"stagePts":{"3":12,"4":8}},{"id":"j-tarling","name":"J. TARLING","bib":"87","cost":16,"cat":"All-rounders","team":11,"total":38,"avg":9.5,"nbMatchs":4,"breakdown":{"finishes":20,"climbsSprints":1,"combativity":0,"gc":7,"points":0,"kom":10,"youth":0},"stagePts":{"3":1,"4":0}},{"id":"f-grossschartner","name":"F. GROSSSCHARTNER","bib":"3","cost":12,"cat":"Climbers","team":20,"total":38,"avg":9.5,"nbMatchs":4,"breakdown":{"finishes":26,"climbsSprints":0,"combativity":0,"gc":12,"points":0,"kom":0,"youth":0},"stagePts":{"3":9,"4":10}},{"id":"v-campenaerts","name":"V. CAMPENAERTS","bib":"14","cost":11,"cat":"All-rounders","team":17,"total":37,"avg":9.2,"nbMatchs":4,"breakdown":{"finishes":32,"climbsSprints":0,"combativity":0,"gc":5,"points":0,"kom":0,"youth":0},"stagePts":{"3":5,"4":6}},{"id":"b-armirail","name":"B. ARMIRAIL","bib":"13","cost":11,"cat":"All-rounders","team":17,"total":37,"avg":9.2,"nbMatchs":4,"breakdown":{"finishes":33,"climbsSprints":0,"combativity":0,"gc":4,"points":0,"kom":0,"youth":0},"stagePts":{"3":0,"4":4}},{"id":"j-romo oliver","name":"J. ROMO OLIVER","bib":"147","cost":7,"cat":"All-rounders","team":9,"total":32,"avg":8.0,"nbMatchs":4,"breakdown":{"finishes":10,"climbsSprints":5,"combativity":0,"gc":17,"points":0,"kom":0,"youth":0},"stagePts":{"3":11,"4":3}},{"id":"c-verona quintanilla","name":"C. VERONA QUINTANILLA","bib":"38","cost":6,"cat":"All-rounders","team":7,"total":31,"avg":7.8,"nbMatchs":4,"breakdown":{"finishes":22,"climbsSprints":0,"combativity":0,"gc":9,"points":0,"kom":0,"youth":0},"stagePts":{"3":9,"4":9}},{"id":"p-hagenes","name":"P. HAGENES","bib":"15","cost":10,"cat":"Climbers","team":17,"total":30,"avg":7.5,"nbMatchs":4,"breakdown":{"finishes":30,"climbsSprints":0,"combativity":0,"gc":0,"points":0,"kom":0,"youth":0},"stagePts":{"3":0,"4":5}},{"id":"e-affini","name":"E. AFFINI","bib":"12","cost":14,"cat":"All-rounders","team":17,"total":29,"avg":7.2,"nbMatchs":4,"breakdown":{"finishes":29,"climbsSprints":0,"combativity":0,"gc":0,"points":0,"kom":0,"youth":0},"stagePts":{"3":0,"4":4}},{"id":"t-wellens","name":"T. WELLENS","bib":"7","cost":12,"cat":"All-rounders","team":20,"total":29,"avg":7.2,"nbMatchs":4,"breakdown":{"finishes":22,"climbsSprints":2,"combativity":0,"gc":5,"points":0,"kom":0,"youth":0},"stagePts":{"3":3,"4":5}},{"id":"a-skaarseth","name":"A. SKAARSETH","bib":"126","cost":8,"cat":"All-rounders","team":21,"total":28,"avg":7.0,"nbMatchs":4,"breakdown":{"finishes":14,"climbsSprints":0,"combativity":0,"gc":14,"points":0,"kom":0,"youth":0},"stagePts":{"3":10,"4":7}},{"id":"c-harper","name":"C. HARPER","bib":"173","cost":10,"cat":"Climbers","team":12,"total":27,"avg":6.8,"nbMatchs":4,"breakdown":{"finishes":14,"climbsSprints":0,"combativity":0,"gc":13,"points":0,"kom":0,"youth":0},"stagePts":{"3":11,"4":6}},{"id":"m-cattaneo","name":"M. CATTANEO","bib":"22","cost":11,"cat":"All-rounders","team":13,"total":25,"avg":6.2,"nbMatchs":4,"breakdown":{"finishes":19,"climbsSprints":0,"combativity":0,"gc":6,"points":0,"kom":0,"youth":0},"stagePts":{"3":6,"4":5}},{"id":"n-breuillard","name":"N. BREUILLARD","bib":"202","cost":7,"cat":"Climbers","team":18,"total":25,"avg":6.2,"nbMatchs":4,"breakdown":{"finishes":9,"climbsSprints":2,"combativity":0,"gc":14,"points":0,"kom":0,"youth":0},"stagePts":{"3":11,"4":4}},{"id":"t-skujins","name":"T. SKUJINS","bib":"36","cost":9,"cat":"All-rounders","team":7,"total":24,"avg":6.0,"nbMatchs":4,"breakdown":{"finishes":21,"climbsSprints":0,"combativity":0,"gc":3,"points":0,"kom":0,"youth":0},"stagePts":{"3":4,"4":7}},{"id":"b-oconnor","name":"B. O'CONNOR","bib":"111","cost":16,"cat":"Leaders","team":15,"total":23,"avg":5.8,"nbMatchs":4,"breakdown":{"finishes":14,"climbsSprints":0,"combativity":0,"gc":9,"points":0,"kom":0,"youth":0},"stagePts":{"3":4,"4":3}},{"id":"m-hirschi","name":"M. HIRSCHI","bib":"194","cost":11,"cat":"All-rounders","team":19,"total":23,"avg":5.8,"nbMatchs":4,"breakdown":{"finishes":8,"climbsSprints":0,"combativity":0,"gc":15,"points":0,"kom":0,"youth":0},"stagePts":{"3":7,"4":3}},{"id":"l-germani","name":"L. GERMANI","bib":"185","cost":8,"cat":"All-rounders","team":6,"total":23,"avg":5.8,"nbMatchs":4,"breakdown":{"finishes":15,"climbsSprints":0,"combativity":0,"gc":8,"points":0,"kom":0,"youth":0},"stagePts":{"3":6,"4":4}},{"id":"d-caruso","name":"D. CARUSO","bib":"73","cost":11,"cat":"Climbers","team":1,"total":22,"avg":5.5,"nbMatchs":4,"breakdown":{"finishes":14,"climbsSprints":0,"combativity":0,"gc":8,"points":0,"kom":0,"youth":0},"stagePts":{"3":5,"4":5}},{"id":"e-verstrynge","name":"E. VERSTRYNGE","bib":"108","cost":9,"cat":"All-rounders","team":0,"total":21,"avg":5.2,"nbMatchs":4,"breakdown":{"finishes":11,"climbsSprints":0,"combativity":0,"gc":10,"points":0,"kom":0,"youth":0},"stagePts":{"3":1,"4":1}},{"id":"m-le berre","name":"M. LE BERRE","bib":"206","cost":9,"cat":"All-rounders","team":18,"total":20,"avg":5.0,"nbMatchs":4,"breakdown":{"finishes":8,"climbsSprints":4,"combativity":0,"gc":8,"points":0,"kom":0,"youth":0},"stagePts":{"3":7,"4":3}},{"id":"k-asgreen","name":"K. ASGREEN","bib":"42","cost":11,"cat":"All-rounders","team":5,"total":19,"avg":4.8,"nbMatchs":4,"breakdown":{"finishes":12,"climbsSprints":0,"combativity":0,"gc":7,"points":0,"kom":0,"youth":0},"stagePts":{"3":6,"4":4}},{"id":"f-vermeersch","name":"F. VERMEERSCH","bib":"6","cost":10,"cat":"All-rounders","team":20,"total":19,"avg":4.8,"nbMatchs":4,"breakdown":{"finishes":15,"climbsSprints":4,"combativity":0,"gc":0,"points":0,"kom":0,"youth":0},"stagePts":{"3":0,"4":0}},{"id":"x-meurisse","name":"X. MEURISSE","bib":"176","cost":9,"cat":"Climbers","team":12,"total":18,"avg":4.5,"nbMatchs":4,"breakdown":{"finishes":12,"climbsSprints":0,"combativity":0,"gc":6,"points":0,"kom":0,"youth":0},"stagePts":{"3":5,"4":4}},{"id":"j-alaphilippe","name":"J. ALAPHILIPPE","bib":"191","cost":15,"cat":"All-rounders","team":19,"total":17,"avg":4.2,"nbMatchs":4,"breakdown":{"finishes":5,"climbsSprints":0,"combativity":0,"gc":12,"points":0,"kom":0,"youth":0},"stagePts":{"3":0,"4":1}},{"id":"n-politt","name":"N. POLITT","bib":"5","cost":10,"cat":"All-rounders","team":20,"total":17,"avg":4.2,"nbMatchs":4,"breakdown":{"finishes":17,"climbsSprints":0,"combativity":0,"gc":0,"points":0,"kom":0,"youth":0},"stagePts":{"3":2,"4":0}},{"id":"d-van baarle","name":"D. VAN BAARLE","bib":"95","cost":10,"cat":"All-rounders","team":14,"total":17,"avg":4.2,"nbMatchs":4,"breakdown":{"finishes":7,"climbsSprints":0,"combativity":0,"gc":10,"points":0,"kom":0,"youth":0},"stagePts":{"3":3,"4":0}},{"id":"q-pacher","name":"Q. PACHER","bib":"187","cost":10,"cat":"All-rounders","team":6,"total":16,"avg":4.0,"nbMatchs":4,"breakdown":{"finishes":12,"climbsSprints":0,"combativity":0,"gc":4,"points":0,"kom":0,"youth":0},"stagePts":{"3":2,"4":0}},{"id":"a-turgis","name":"A. TURGIS","bib":"207","cost":10,"cat":"All-rounders","team":18,"total":16,"avg":4.0,"nbMatchs":4,"breakdown":{"finishes":4,"climbsSprints":12,"combativity":0,"gc":0,"points":0,"kom":0,"youth":0},"stagePts":{"3":0,"4":0}},{"id":"t-merlier","name":"T. MERLIER","bib":"91","cost":23,"cat":"Sprinters","team":14,"total":15,"avg":3.8,"nbMatchs":4,"breakdown":{"finishes":5,"climbsSprints":10,"combativity":0,"gc":0,"points":0,"kom":0,"youth":0},"stagePts":{"3":0,"4":0}},{"id":"t-van dijke","name":"T. VAN DIJKE","bib":"27","cost":10,"cat":"All-rounders","team":13,"total":15,"avg":3.8,"nbMatchs":4,"breakdown":{"finishes":15,"climbsSprints":0,"combativity":0,"gc":0,"points":0,"kom":0,"youth":0},"stagePts":{"3":0,"4":3}},{"id":"r-dhondt","name":"R. DHONDT","bib":"215","cost":5,"cat":"All-rounders","team":16,"total":15,"avg":3.8,"nbMatchs":4,"breakdown":{"finishes":4,"climbsSprints":0,"combativity":0,"gc":10,"points":0,"kom":0,"youth":1},"stagePts":{"3":0,"4":0}},{"id":"j-cepeda","name":"J. CEPEDA","bib":"143","cost":11,"cat":"Climbers","team":9,"total":14,"avg":3.5,"nbMatchs":4,"breakdown":{"finishes":5,"climbsSprints":0,"combativity":0,"gc":9,"points":0,"kom":0,"youth":0},"stagePts":{"3":3,"4":2}},{"id":"d-hoole","name":"D. HOOLE","bib":"54","cost":10,"cat":"All-rounders","team":4,"total":14,"avg":3.5,"nbMatchs":4,"breakdown":{"finishes":14,"climbsSprints":0,"combativity":0,"gc":0,"points":0,"kom":0,"youth":0},"stagePts":{"3":0,"4":4}},{"id":"c-russo","name":"C. RUSSO","bib":"188","cost":9,"cat":"All-rounders","team":6,"total":14,"avg":3.5,"nbMatchs":4,"breakdown":{"finishes":12,"climbsSprints":0,"combativity":0,"gc":2,"points":0,"kom":0,"youth":0},"stagePts":{"3":1,"4":1}},{"id":"a-johannessen","name":"A. JOHANNESSEN","bib":"125","cost":6,"cat":"All-rounders","team":21,"total":14,"avg":3.5,"nbMatchs":4,"breakdown":{"finishes":10,"climbsSprints":0,"combativity":0,"gc":4,"points":0,"kom":0,"youth":0},"stagePts":{"3":0,"4":2}},{"id":"b-healy","name":"B. HEALY","bib":"44","cost":15,"cat":"All-rounders","team":5,"total":13,"avg":3.2,"nbMatchs":4,"breakdown":{"finishes":10,"climbsSprints":0,"combativity":0,"gc":3,"points":0,"kom":0,"youth":0},"stagePts":{"3":2,"4":3}},{"id":"r-pluimers","name":"R. PLUIMERS","bib":"195","cost":9,"cat":"All-rounders","team":19,"total":13,"avg":3.2,"nbMatchs":4,"breakdown":{"finishes":8,"climbsSprints":0,"combativity":0,"gc":5,"points":0,"kom":0,"youth":0},"stagePts":{"3":2,"4":2}},{"id":"s-berwick","name":"S. BERWICK","bib":"223","cost":8,"cat":"Climbers","team":2,"total":13,"avg":3.2,"nbMatchs":4,"breakdown":{"finishes":7,"climbsSprints":0,"combativity":0,"gc":6,"points":0,"kom":0,"youth":0},"stagePts":{"3":3,"4":1}},{"id":"j-abrahamsen","name":"J. ABRAHAMSEN","bib":"122","cost":12,"cat":"All-rounders","team":21,"total":12,"avg":3.0,"nbMatchs":4,"breakdown":{"finishes":9,"climbsSprints":2,"combativity":0,"gc":1,"points":0,"kom":0,"youth":0},"stagePts":{"3":5,"4":2}},{"id":"s-waerenskjold","name":"S. WÆRENSKJOLD","bib":"128","cost":11,"cat":"All-rounders","team":21,"total":11,"avg":2.8,"nbMatchs":4,"breakdown":{"finishes":5,"climbsSprints":6,"combativity":0,"gc":0,"points":0,"kom":0,"youth":0},"stagePts":{"3":0,"4":0}},{"id":"o-kooij","name":"O. KOOIJ","bib":"55","cost":19,"cat":"Sprinters","team":4,"total":10,"avg":2.5,"nbMatchs":4,"breakdown":{"finishes":10,"climbsSprints":0,"combativity":0,"gc":0,"points":0,"kom":0,"youth":0},"stagePts":{"3":0,"4":0}},{"id":"m-mohoric","name":"M. MOHORIC","bib":"75","cost":16,"cat":"All-rounders","team":1,"total":10,"avg":2.5,"nbMatchs":4,"breakdown":{"finishes":10,"climbsSprints":0,"combativity":0,"gc":0,"points":0,"kom":0,"youth":0},"stagePts":{"3":0,"4":2}},{"id":"m-kanter","name":"M. KANTER","bib":"64","cost":13,"cat":"Sprinters","team":22,"total":10,"avg":2.5,"nbMatchs":4,"breakdown":{"finishes":1,"climbsSprints":8,"combativity":0,"gc":1,"points":0,"kom":0,"youth":0},"stagePts":{"3":0,"4":0}},{"id":"c-bol","name":"C. BOL","bib":"53","cost":11,"cat":"Sprinters","team":4,"total":10,"avg":2.5,"nbMatchs":4,"breakdown":{"finishes":10,"climbsSprints":0,"combativity":0,"gc":0,"points":0,"kom":0,"youth":0},"stagePts":{"3":0,"4":0}},{"id":"s-dillier","name":"S. DILLIER","bib":"103","cost":8,"cat":"All-rounders","team":0,"total":10,"avg":2.5,"nbMatchs":4,"breakdown":{"finishes":10,"climbsSprints":0,"combativity":0,"gc":0,"points":0,"kom":0,"youth":0},"stagePts":{"3":1,"4":0}},{"id":"t-marsman","name":"T. MARSMAN","bib":"104","cost":5,"cat":"All-rounders","team":0,"total":10,"avg":2.5,"nbMatchs":4,"breakdown":{"finishes":9,"climbsSprints":0,"combativity":0,"gc":1,"points":0,"kom":0,"youth":0},"stagePts":{"3":0,"4":0}},{"id":"t-guernalec","name":"T. GUERNALEC","bib":"205","cost":10,"cat":"All-rounders","team":18,"total":9,"avg":2.2,"nbMatchs":4,"breakdown":{"finishes":6,"climbsSprints":3,"combativity":0,"gc":0,"points":0,"kom":0,"youth":0},"stagePts":{"3":3,"4":0}},{"id":"j-rickaert","name":"J. RICKAERT","bib":"107","cost":8,"cat":"All-rounders","team":0,"total":9,"avg":2.2,"nbMatchs":4,"breakdown":{"finishes":9,"climbsSprints":0,"combativity":0,"gc":0,"points":0,"kom":0,"youth":0},"stagePts":{"3":0,"4":0}},{"id":"a-charmig","name":"A. CHARMIG","bib":"123","cost":8,"cat":"Climbers","team":21,"total":9,"avg":2.2,"nbMatchs":4,"breakdown":{"finishes":8,"climbsSprints":0,"combativity":0,"gc":1,"points":0,"kom":0,"youth":0},"stagePts":{"3":1,"4":2}},{"id":"m-walker","name":"M. WALKER","bib":"48","cost":6,"cat":"All-rounders","team":5,"total":9,"avg":2.2,"nbMatchs":4,"breakdown":{"finishes":9,"climbsSprints":0,"combativity":0,"gc":0,"points":0,"kom":0,"youth":0},"stagePts":{"3":0,"4":2}},{"id":"p-bauhaus","name":"P. BAUHAUS","bib":"72","cost":15,"cat":"Sprinters","team":1,"total":8,"avg":2.0,"nbMatchs":4,"breakdown":{"finishes":8,"climbsSprints":0,"combativity":0,"gc":0,"points":0,"kom":0,"youth":0},"stagePts":{"3":0,"4":0}},{"id":"e-rubio reyes","name":"E. RUBIO REYES","bib":"148","cost":14,"cat":"Climbers","team":9,"total":8,"avg":2.0,"nbMatchs":4,"breakdown":{"finishes":5,"climbsSprints":0,"combativity":0,"gc":3,"points":0,"kom":0,"youth":0},"stagePts":{"3":5,"4":1}},{"id":"j-berckmoes","name":"J. BERCKMOES","bib":"153","cost":13,"cat":"Sprinters","team":8,"total":8,"avg":2.0,"nbMatchs":4,"breakdown":{"finishes":2,"climbsSprints":0,"combativity":0,"gc":6,"points":0,"kom":0,"youth":0},"stagePts":{"3":2,"4":0}},{"id":"a-wright","name":"A. WRIGHT","bib":"178","cost":12,"cat":"All-rounders","team":12,"total":8,"avg":2.0,"nbMatchs":4,"breakdown":{"finishes":8,"climbsSprints":0,"combativity":0,"gc":0,"points":0,"kom":0,"youth":0},"stagePts":{"3":0,"4":2}},{"id":"d-howson","name":"D. HOWSON","bib":"175","cost":8,"cat":"Climbers","team":12,"total":8,"avg":2.0,"nbMatchs":4,"breakdown":{"finishes":7,"climbsSprints":0,"combativity":0,"gc":1,"points":0,"kom":0,"youth":0},"stagePts":{"3":1,"4":0}},{"id":"l-durbridge","name":"L. DURBRIDGE","bib":"113","cost":7,"cat":"All-rounders","team":15,"total":8,"avg":2.0,"nbMatchs":4,"breakdown":{"finishes":8,"climbsSprints":0,"combativity":0,"gc":0,"points":0,"kom":0,"youth":0},"stagePts":{"3":0,"4":0}},{"id":"x-azparren irurzun","name":"X. AZPARREN IRURZUN","bib":"172","cost":7,"cat":"All-rounders","team":12,"total":8,"avg":2.0,"nbMatchs":4,"breakdown":{"finishes":8,"climbsSprints":0,"combativity":0,"gc":0,"points":0,"kom":0,"youth":0},"stagePts":{"3":0,"4":2}},{"id":"k-gradek","name":"K. GRADEK","bib":"74","cost":5,"cat":"All-rounders","team":1,"total":8,"avg":2.0,"nbMatchs":4,"breakdown":{"finishes":8,"climbsSprints":0,"combativity":0,"gc":0,"points":0,"kom":0,"youth":0},"stagePts":{"3":0,"4":0}},{"id":"p-ackermann","name":"P. ACKERMANN","bib":"112","cost":15,"cat":"Sprinters","team":15,"total":7,"avg":1.8,"nbMatchs":4,"breakdown":{"finishes":7,"climbsSprints":0,"combativity":0,"gc":0,"points":0,"kom":0,"youth":0},"stagePts":{"3":0,"4":0}},{"id":"d-ballerini","name":"D. BALLERINI","bib":"62","cost":12,"cat":"All-rounders","team":22,"total":6,"avg":1.5,"nbMatchs":4,"breakdown":{"finishes":1,"climbsSprints":5,"combativity":0,"gc":0,"points":0,"kom":0,"youth":0},"stagePts":{"3":0,"4":0}},{"id":"s-oldani","name":"S. OLDANI","bib":"226","cost":8,"cat":"Sprinters","team":2,"total":6,"avg":1.5,"nbMatchs":4,"breakdown":{"finishes":5,"climbsSprints":0,"combativity":0,"gc":1,"points":0,"kom":0,"youth":0},"stagePts":{"3":2,"4":0}},{"id":"l-craps","name":"L. CRAPS","bib":"154","cost":8,"cat":"All-rounders","team":8,"total":6,"avg":1.5,"nbMatchs":4,"breakdown":{"finishes":3,"climbsSprints":0,"combativity":0,"gc":3,"points":0,"kom":0,"youth":0},"stagePts":{"3":1,"4":0}},{"id":"m-hessmann","name":"M. HEßMANN","bib":"145","cost":8,"cat":"All-rounders","team":9,"total":6,"avg":1.5,"nbMatchs":4,"breakdown":{"finishes":2,"climbsSprints":0,"combativity":0,"gc":4,"points":0,"kom":0,"youth":0},"stagePts":{"3":0,"4":0}},{"id":"s-velasco","name":"S. VELASCO","bib":"67","cost":11,"cat":"All-rounders","team":22,"total":5,"avg":1.2,"nbMatchs":4,"breakdown":{"finishes":3,"climbsSprints":0,"combativity":0,"gc":2,"points":0,"kom":0,"youth":0},"stagePts":{"3":3,"4":1}},{"id":"b-thomas","name":"B. THOMAS","bib":"168","cost":10,"cat":"All-rounders","team":3,"total":5,"avg":1.2,"nbMatchs":4,"breakdown":{"finishes":3,"climbsSprints":0,"combativity":0,"gc":2,"points":0,"kom":0,"youth":0},"stagePts":{"3":0,"4":0}},{"id":"j-otruba","name":"J. OTRUBA","bib":"227","cost":8,"cat":"All-rounders","team":2,"total":5,"avg":1.2,"nbMatchs":4,"breakdown":{"finishes":5,"climbsSprints":0,"combativity":0,"gc":0,"points":0,"kom":0,"youth":0},"stagePts":{"3":1,"4":0}},{"id":"b-van lerberghe","name":"B. VAN LERBERGHE","bib":"96","cost":6,"cat":"All-rounders","team":14,"total":5,"avg":1.2,"nbMatchs":4,"breakdown":{"finishes":5,"climbsSprints":0,"combativity":0,"gc":0,"points":0,"kom":0,"youth":0},"stagePts":{"3":0,"4":0}},{"id":"f-gaviria rendon","name":"F. GAVIRIA RENDON","bib":"221","cost":14,"cat":"Sprinters","team":2,"total":4,"avg":1.0,"nbMatchs":4,"breakdown":{"finishes":4,"climbsSprints":0,"combativity":0,"gc":0,"points":0,"kom":0,"youth":0},"stagePts":{"3":0,"4":0}},{"id":"l-slock","name":"L. SLOCK","bib":"155","cost":9,"cat":"All-rounders","team":8,"total":4,"avg":1.0,"nbMatchs":4,"breakdown":{"finishes":1,"climbsSprints":3,"combativity":0,"gc":0,"points":0,"kom":0,"youth":0},"stagePts":{"3":3,"4":0}},{"id":"n-markl","name":"N. MÄRKL","bib":"216","cost":6,"cat":"All-rounders","team":16,"total":4,"avg":1.0,"nbMatchs":4,"breakdown":{"finishes":2,"climbsSprints":0,"combativity":0,"gc":2,"points":0,"kom":0,"youth":0},"stagePts":{"3":0,"4":0}},{"id":"a-de kleijn","name":"A. DE KLEIJN","bib":"192","cost":15,"cat":"Sprinters","team":19,"total":3,"avg":0.8,"nbMatchs":4,"breakdown":{"finishes":3,"climbsSprints":0,"combativity":0,"gc":0,"points":0,"kom":0,"youth":0},"stagePts":{"3":0,"4":0}},{"id":"l-askey","name":"L. ASKEY","bib":"132","cost":13,"cat":"All-rounders","team":10,"total":3,"avg":0.8,"nbMatchs":4,"breakdown":{"finishes":2,"climbsSprints":0,"combativity":0,"gc":1,"points":0,"kom":0,"youth":0},"stagePts":{"3":0,"4":0}},{"id":"p-bittner","name":"P. BITTNER","bib":"213","cost":13,"cat":"Sprinters","team":16,"total":3,"avg":0.8,"nbMatchs":4,"breakdown":{"finishes":1,"climbsSprints":0,"combativity":0,"gc":2,"points":0,"kom":0,"youth":0},"stagePts":{"3":0,"4":0}},{"id":"m-trentin","name":"M. TRENTIN","bib":"197","cost":12,"cat":"Sprinters","team":19,"total":3,"avg":0.8,"nbMatchs":4,"breakdown":{"finishes":3,"climbsSprints":0,"combativity":0,"gc":0,"points":0,"kom":0,"youth":0},"stagePts":{"3":0,"4":0}},{"id":"k-neilands","name":"K. NEILANDS","bib":"136","cost":11,"cat":"All-rounders","team":10,"total":3,"avg":0.8,"nbMatchs":4,"breakdown":{"finishes":2,"climbsSprints":0,"combativity":0,"gc":1,"points":0,"kom":0,"youth":0},"stagePts":{"3":0,"4":0}},{"id":"w-barguil","name":"W. BARGUIL","bib":"211","cost":10,"cat":"Climbers","team":16,"total":3,"avg":0.8,"nbMatchs":4,"breakdown":{"finishes":1,"climbsSprints":0,"combativity":0,"gc":2,"points":0,"kom":0,"youth":0},"stagePts":{"3":0,"4":0}},{"id":"j-degenkolb","name":"J. DEGENKOLB","bib":"214","cost":10,"cat":"Sprinters","team":16,"total":3,"avg":0.8,"nbMatchs":4,"breakdown":{"finishes":1,"climbsSprints":0,"combativity":0,"gc":2,"points":0,"kom":0,"youth":0},"stagePts":{"3":0,"4":0}},{"id":"a-gate","name":"A. GATE","bib":"63","cost":10,"cat":"Sprinters","team":22,"total":3,"avg":0.8,"nbMatchs":4,"breakdown":{"finishes":3,"climbsSprints":0,"combativity":0,"gc":0,"points":0,"kom":0,"youth":0},"stagePts":{"3":0,"4":1}},{"id":"m-teunissen","name":"M. TEUNISSEN","bib":"66","cost":9,"cat":"All-rounders","team":22,"total":3,"avg":0.8,"nbMatchs":4,"breakdown":{"finishes":3,"climbsSprints":0,"combativity":0,"gc":0,"points":0,"kom":0,"youth":0},"stagePts":{"3":1,"4":0}},{"id":"t-van asbroeck","name":"T. VAN ASBROECK","bib":"138","cost":9,"cat":"All-rounders","team":10,"total":3,"avg":0.8,"nbMatchs":4,"breakdown":{"finishes":2,"climbsSprints":0,"combativity":0,"gc":1,"points":0,"kom":0,"youth":0},"stagePts":{"3":0,"4":0}},{"id":"f-biesterbos","name":"F. BIESTERBOS","bib":"212","cost":9,"cat":"All-rounders","team":16,"total":3,"avg":0.8,"nbMatchs":4,"breakdown":{"finishes":1,"climbsSprints":0,"combativity":0,"gc":2,"points":0,"kom":0,"youth":0},"stagePts":{"3":0,"4":0}},{"id":"m-haller","name":"M. HALLER","bib":"193","cost":8,"cat":"All-rounders","team":19,"total":3,"avg":0.8,"nbMatchs":4,"breakdown":{"finishes":3,"climbsSprints":0,"combativity":0,"gc":0,"points":0,"kom":0,"youth":0},"stagePts":{"3":0,"4":0}},{"id":"j-van den berg","name":"J. VAN DEN BERG","bib":"217","cost":6,"cat":"All-rounders","team":16,"total":3,"avg":0.8,"nbMatchs":4,"breakdown":{"finishes":1,"climbsSprints":0,"combativity":0,"gc":2,"points":0,"kom":0,"youth":0},"stagePts":{"3":0,"4":0}},{"id":"t-stewart","name":"T. STEWART","bib":"137","cost":15,"cat":"Sprinters","team":10,"total":2,"avg":0.5,"nbMatchs":4,"breakdown":{"finishes":2,"climbsSprints":0,"combativity":0,"gc":0,"points":0,"kom":0,"youth":0},"stagePts":{"3":0,"4":0}},{"id":"m-fretin","name":"M. FRETIN","bib":"165","cost":14,"cat":"Sprinters","team":3,"total":2,"avg":0.5,"nbMatchs":4,"breakdown":{"finishes":2,"climbsSprints":0,"combativity":0,"gc":0,"points":0,"kom":0,"youth":0},"stagePts":{"3":0,"4":0}},{"id":"h-page","name":"H. PAGE","bib":"167","cost":11,"cat":"Sprinters","team":3,"total":2,"avg":0.5,"nbMatchs":4,"breakdown":{"finishes":2,"climbsSprints":0,"combativity":0,"gc":0,"points":0,"kom":0,"youth":0},"stagePts":{"3":0,"4":0}},{"id":"j-biermans","name":"J. BIERMANS","bib":"164","cost":7,"cat":"All-rounders","team":3,"total":2,"avg":0.5,"nbMatchs":4,"breakdown":{"finishes":2,"climbsSprints":0,"combativity":0,"gc":0,"points":0,"kom":0,"youth":0},"stagePts":{"3":0,"4":0}},{"id":"m-louvel","name":"M. LOUVEL","bib":"135","cost":7,"cat":"All-rounders","team":10,"total":2,"avg":0.5,"nbMatchs":4,"breakdown":{"finishes":2,"climbsSprints":0,"combativity":0,"gc":0,"points":0,"kom":0,"youth":0},"stagePts":{"3":0,"4":0}},{"id":"p-allegaert","name":"P. ALLEGAERT","bib":"162","cost":6,"cat":"All-rounders","team":3,"total":2,"avg":0.5,"nbMatchs":4,"breakdown":{"finishes":2,"climbsSprints":0,"combativity":0,"gc":0,"points":0,"kom":0,"youth":0},"stagePts":{"3":0,"4":0}},{"id":"b-veistroffer","name":"B. VEISTROFFER","bib":"157","cost":9,"cat":"All-rounders","team":8,"total":1,"avg":0.2,"nbMatchs":4,"breakdown":{"finishes":1,"climbsSprints":0,"combativity":0,"gc":0,"points":0,"kom":0,"youth":0},"stagePts":{"3":0,"4":0}},{"id":"h-artz","name":"H. ARTZ","bib":"152","cost":8,"cat":"All-rounders","team":8,"total":1,"avg":0.2,"nbMatchs":4,"breakdown":{"finishes":1,"climbsSprints":0,"combativity":0,"gc":0,"points":0,"kom":0,"youth":0},"stagePts":{"3":0,"4":0}},{"id":"n-vinokurov","name":"N. VINOKUROV","bib":"68","cost":8,"cat":"All-rounders","team":22,"total":1,"avg":0.2,"nbMatchs":4,"breakdown":{"finishes":1,"climbsSprints":0,"combativity":0,"gc":0,"points":0,"kom":0,"youth":0},"stagePts":{"3":0,"4":0}}],"stages":[{"n":1,"name":"1 - Barcelone > Barcelone","info":"TYPE=PASE;DISTANCE=19","myRank":4,"top10":[{"name":"J. Vingegaard","team":"Team Visma | Lease A Bike","bib":"11","time":"00h 21' 47''","gap":"-"},{"name":"F. Ganna","team":"Netcompany Ineos Cycling Team","bib":"84","time":"00h 21' 55''","gap":"+ 00h 00' 08''"},{"name":"T. Pogacar","team":"Uae Team Emirates Xrg","bib":"1","time":"00h 21' 59''","gap":"+ 00h 00' 12''"},{"name":"J. Ayuso","team":"Lidl-Trek","bib":"31","time":"00h 22' 03''","gap":"+ 00h 00' 16''"},{"name":"R. Evenepoel","team":"Red Bull - Bora - Hansgrohe","bib":"21","time":"00h 22' 06''","gap":"+ 00h 00' 19''"},{"name":"I. Del Toro","team":"Uae Team Emirates Xrg","bib":"2","time":"00h 22' 13''","gap":"+ 00h 00' 26''"},{"name":"D. Piganzoli","team":"Team Visma | Lease A Bike","bib":"18","time":"00h 22' 15''","gap":"+ 00h 00' 28''"},{"name":"F. Lipowitz","team":"Red Bull - Bora - Hansgrohe","bib":"25","time":"00h 22' 22''","gap":"+ 00h 00' 35''"},{"name":"T. Foss","team":"Netcompany Ineos Cycling Team","bib":"83","time":"00h 22' 25''","gap":"+ 00h 00' 38''"},{"name":"P. Seixas","team":"Decathlon Cma Cgm Team","bib":"51","time":"00h 22' 26''","gap":"+ 00h 00' 39''"}],"gcTop10":[{"name":"J. Vingegaard","team":"Team Visma | Lease A Bike","bib":"11","gap":"-"},{"name":"F. Ganna","team":"Netcompany Ineos Cycling Team","bib":"84","gap":"+ 00h 00' 08''"},{"name":"T. Pogacar","team":"Uae Team Emirates Xrg","bib":"1","gap":"+ 00h 00' 12''"},{"name":"J. Ayuso","team":"Lidl-Trek","bib":"31","gap":"+ 00h 00' 16''"},{"name":"R. Evenepoel","team":"Red Bull - Bora - Hansgrohe","bib":"21","gap":"+ 00h 00' 19''"},{"name":"I. Del Toro","team":"Uae Team Emirates Xrg","bib":"2","gap":"+ 00h 00' 26''"},{"name":"D. Piganzoli","team":"Team Visma | Lease A Bike","bib":"18","gap":"+ 00h 00' 28''"},{"name":"F. Lipowitz","team":"Red Bull - Bora - Hansgrohe","bib":"25","gap":"+ 00h 00' 35''"},{"name":"T. Foss","team":"Netcompany Ineos Cycling Team","bib":"83","gap":"+ 00h 00' 38''"},{"name":"P. Seixas","team":"Decathlon Cma Cgm Team","bib":"51","gap":"+ 00h 00' 39''"}],"jerseys":{"gc":{"name":"J. Vingegaard","team":"Team Visma | Lease A Bike","bib":"11"},"points":{"name":"E. Bernal","team":"Netcompany Ineos Cycling Team","bib":"81"},"kom":{"name":"T. Pogacar","team":"Uae Team Emirates Xrg","bib":"1"},"youth":{"name":"J. Ayuso","team":"Lidl-Trek","bib":"31"}},"combativity":null,"finishers":184},{"n":2,"name":"2 - Tarragone > Barcelone","info":"TYPE=VAL;DISTANCE=182","myRank":1,"top10":[{"name":"I. Del Toro","team":"Uae Team Emirates Xrg","bib":"2","time":"03h 40' 01''","gap":"-"},{"name":"T. Pogacar","team":"Uae Team Emirates Xrg","bib":"1","time":"03h 40' 01''","gap":"-"},{"name":"R. Evenepoel","team":"Red Bull - Bora - Hansgrohe","bib":"21","time":"03h 40' 01''","gap":"-"},{"name":"J. Vingegaard","team":"Team Visma | Lease A Bike","bib":"11","time":"03h 40' 01''","gap":"-"},{"name":"M. Skjelmose","team":"Lidl-Trek","bib":"35","time":"03h 40' 04''","gap":"+ 00h 00' 03''"},{"name":"T. Johannessen","team":"Uno-X Mobility","bib":"121","time":"03h 40' 04''","gap":"+ 00h 00' 03''"},{"name":"R. Gregoire","team":"Groupama-Fdj United","bib":"181","time":"03h 40' 04''","gap":"+ 00h 00' 03''"},{"name":"L. Martinez","team":"Bahrain Victorious","bib":"71","time":"03h 40' 04''","gap":"+ 00h 00' 03''"},{"name":"P. Seixas","team":"Decathlon Cma Cgm Team","bib":"51","time":"03h 40' 04''","gap":"+ 00h 00' 03''"},{"name":"T. Pidcock","team":"Pinarello-Q36.5 Pro Cycling Team","bib":"171","time":"03h 40' 04''","gap":"+ 00h 00' 03''"}],"gcTop10":[],"jerseys":{},"combativity":{"name":"F. Engelhardt","team":"Team Jayco Alula","bib":"114"},"finishers":183},{"n":3,"name":"3 - Granollers > Les Angles","info":"TYPE=HMG;DISTANCE=196","myRank":3,"top10":[{"name":"T. Pogacar","team":"Uae Team Emirates Xrg","bib":"1","time":"04h 45' 11''","gap":"-"},{"name":"J. Vingegaard","team":"Team Visma | Lease A Bike","bib":"11","time":"04h 45' 13''","gap":"+ 00h 00' 02''"},{"name":"R. Carapaz","team":"Ef Education - Easypost","bib":"41","time":"04h 45' 13''","gap":"+ 00h 00' 02''"},{"name":"P. Seixas","team":"Decathlon Cma Cgm Team","bib":"51","time":"04h 45' 13''","gap":"+ 00h 00' 02''"},{"name":"T. Johannessen","team":"Uno-X Mobility","bib":"121","time":"04h 45' 15''","gap":"+ 00h 00' 04''"},{"name":"L. Van Eetvelt","team":"Lotto Intermarche","bib":"156","time":"04h 45' 15''","gap":"+ 00h 00' 04''"},{"name":"F. Lipowitz","team":"Red Bull - Bora - Hansgrohe","bib":"25","time":"04h 45' 15''","gap":"+ 00h 00' 04''"},{"name":"R. Evenepoel","team":"Red Bull - Bora - Hansgrohe","bib":"21","time":"04h 45' 15''","gap":"+ 00h 00' 04''"},{"name":"I. Del Toro","team":"Uae Team Emirates Xrg","bib":"2","time":"04h 45' 15''","gap":"+ 00h 00' 04''"},{"name":"J. Ayuso","team":"Lidl-Trek","bib":"31","time":"04h 45' 15''","gap":"+ 00h 00' 04''"}],"gcTop10":[],"jerseys":{},"combativity":{"name":"A. Baudin","team":"Ef Education - Easypost","bib":"43"},"finishers":182},{"n":4,"name":"4 - Carcassonne > Foix","info":"TYPE=VAL;DISTANCE=182","myRank":3,"top10":[{"name":"M. Pedersen","team":"Lidl-Trek","bib":"33","time":"04h 10' 45''","gap":"-"},{"name":"Q. Simmons","team":"Lidl-Trek","bib":"34","time":"04h 10' 45''","gap":"-"},{"name":"R. Garcia","team":"Movistar Team","bib":"144","time":"04h 10' 45''","gap":"-"},{"name":"M. Frigo","team":"Nsn Cycling Team","bib":"134","time":"04h 10' 45''","gap":"-"},{"name":"R. Debruyne","team":"Alpecin-Premier Tech","bib":"102","time":"04h 10' 45''","gap":"-"},{"name":"K. Vauquelin","team":"Netcompany Ineos Cycling Team","bib":"88","time":"04h 10' 45''","gap":"-"},{"name":"S. Quinn","team":"Ef Education - Easypost","bib":"45","time":"04h 10' 45''","gap":"-"},{"name":"T. Træen","team":"Uno-X Mobility","bib":"127","time":"04h 10' 45''","gap":"-"},{"name":"P. Castrillo","team":"Movistar Team","bib":"142","time":"04h 10' 45''","gap":"-"},{"name":"M. Vacek","team":"Lidl-Trek","bib":"37","time":"04h 10' 45''","gap":"-"}],"gcTop10":[],"jerseys":{},"combativity":{"name":"P. Castrillo","team":"Movistar Team","bib":"142"},"finishers":181}],"myTeam":{"stages":{"1":{"riders":[{"name":"Tadej POGACAR","bib":"1","points":100,"captain":true,"cost":27},{"name":"Isaac DEL TORO ROMERO","bib":"2","points":61,"captain":false,"cost":22},{"name":"Jasper PHILIPSEN","bib":"105","points":9,"captain":false,"cost":22},{"name":"Mathieu VAN DER POEL","bib":"101","points":29,"captain":false,"cost":22},{"name":"Stefano OLDANI","bib":"226","points":4,"captain":false,"cost":8},{"name":"Carlos VERONA QUINTANILLA","bib":"38","points":13,"captain":false,"cost":6},{"name":"Alex MOLENAAR","bib":"224","points":14,"captain":false,"cost":5},{"name":"Robbe DHONDT","bib":"215","points":7,"captain":false,"cost":5}],"bonusQuestion":107,"ridersTotal":237,"total":344},"2":{"riders":[{"name":"Tadej POGACAR","bib":"1","points":234,"captain":false,"cost":27},{"name":"Isaac DEL TORO ROMERO","bib":"2","points":285,"captain":false,"cost":22},{"name":"Jasper PHILIPSEN","bib":"105","points":16,"captain":false,"cost":22},{"name":"Mathieu VAN DER POEL","bib":"101","points":32,"captain":true,"cost":22},{"name":"Stefano OLDANI","bib":"226","points":0,"captain":false,"cost":8},{"name":"Carlos VERONA QUINTANILLA","bib":"38","points":0,"captain":false,"cost":6},{"name":"Alex MOLENAAR","bib":"224","points":222,"captain":false,"cost":5},{"name":"Robbe DHONDT","bib":"215","points":8,"captain":false,"cost":5}],"bonusQuestion":0,"ridersTotal":797,"total":797},"3":{"riders":[{"name":"Tadej POGACAR","bib":"1","points":498,"captain":true,"cost":27},{"name":"Isaac DEL TORO ROMERO","bib":"2","points":137,"captain":false,"cost":22},{"name":"Jasper PHILIPSEN","bib":"105","points":0,"captain":false,"cost":22},{"name":"Mathieu VAN DER POEL","bib":"101","points":4,"captain":false,"cost":22},{"name":"Stefano OLDANI","bib":"226","points":2,"captain":false,"cost":8},{"name":"Carlos VERONA QUINTANILLA","bib":"38","points":9,"captain":false,"cost":6},{"name":"Alex MOLENAAR","bib":"224","points":32,"captain":false,"cost":5},{"name":"Robbe DHONDT","bib":"215","points":0,"captain":false,"cost":5}],"bonusQuestion":0,"ridersTotal":682,"total":682},"4":{"riders":[{"name":"Tadej POGACAR","bib":"1","points":77,"captain":false,"cost":27},{"name":"Isaac DEL TORO ROMERO","bib":"2","points":64,"captain":false,"cost":22},{"name":"Jasper PHILIPSEN","bib":"105","points":107,"captain":false,"cost":22},{"name":"Mathieu VAN DER POEL","bib":"101","points":3,"captain":true,"cost":22},{"name":"Stefano OLDANI","bib":"226","points":0,"captain":false,"cost":8},{"name":"Carlos VERONA QUINTANILLA","bib":"38","points":9,"captain":false,"cost":6},{"name":"Alex MOLENAAR","bib":"224","points":152,"captain":false,"cost":5},{"name":"Robbe DHONDT","bib":"215","points":0,"captain":false,"cost":5}],"bonusQuestion":0,"ridersTotal":412,"total":412}},"standings":[{"manager":"Matt","position":1,"total":2235.0,"me":true},{"manager":"Bent Fork","position":2,"total":2133.0,"me":false},{"manager":"Peloton de Powless","position":3,"total":2060.0,"me":false},{"manager":"Donto","position":4,"total":1889.0,"me":false},{"manager":"Snow","position":5,"total":1749.0,"me":false},{"manager":"Crow","position":6,"total":1698.0,"me":false}]}}